lazyshell/__init__.py
lazyshell/core.py
lazyshell-0.2.1.dist-info/licenses/LICENSE
lazyshell-0.2.1.dist-info/METADATA
lazyshell-0.2.1.dist-info/WHEEL
lazyshell-0.2.1.dist-info/top_level.txt
lazyshell-0.2.1.dist-info/RECORD
