Metadata-Version: 2.4
Name: lazyshell
Version: 0.2.1
Summary: Lazy optional imports
Author-email: tmarquart <tmarquart@gmail.com>
License: MIT License
Requires-Python: >=3.9
License-File: LICENSE
Dynamic: license-file
